reportify/__init__.py
reportify/embed_html.py
reportify/header.py
reportify/reportify.py
reportify/data/footer.md
reportify/data/header.md
reportify/data/no_code.tpl
reportify/data/custom/custom.css
reportify-1.3.0.dist-info/DESCRIPTION.rst
reportify-1.3.0.dist-info/METADATA
reportify-1.3.0.dist-info/RECORD
reportify-1.3.0.dist-info/WHEEL
reportify-1.3.0.dist-info/entry_points.txt
reportify-1.3.0.dist-info/metadata.json
reportify-1.3.0.dist-info/top_level.txt
