Metadata-Version: 2.0
Name: reportify
Version: 1.3.0
Summary: Generate report-like documents from Jupyter notebooks
Home-page: https://github.com/eddiejessup/reportify
Author: Elliot Marsden
Author-email: elliot.marsden@gmail.com
License: MIT
Keywords: jupyter report data-science analytics
Platform: UNKNOWN
Classifier: Development Status :: 4 - Beta
Classifier: Intended Audience :: Developers
Classifier: License :: OSI Approved :: MIT License
Classifier: Programming Language :: Python :: 2
Classifier: Programming Language :: Python :: 2.7
Classifier: Programming Language :: Python :: 3
Classifier: Programming Language :: Python :: 3.3
Classifier: Programming Language :: Python :: 3.4
Classifier: Programming Language :: Python :: 3.5
Classifier: Programming Language :: Python :: 3.6
Requires-Dist: beautifulsoup4
Requires-Dist: jupyter
Requires-Dist: jupyter-contrib-nbextensions
Requires-Dist: nbconvert
Requires-Dist: nbformat
Requires-Dist: traitlets
Requires-Dist: PyYAML
Requires-Dist: Jinja2
